ipelago/__init__.py
ipelago/db.py
ipelago/gui.py
ipelago/main.py
ipelago/model.py
ipelago/parser.py
ipelago/publish.py
ipelago/shortid.py
ipelago/stmt.py
ipelago/util.py
ipelago/templates/atom.xml
ipelago/templates/index.html
ipelago/templates/simple.css
ipelago/templates/style.css
ipelago-0.0.6.dist-info/entry_points.txt
ipelago-0.0.6.dist-info/LICENSE
ipelago-0.0.6.dist-info/WHEEL
ipelago-0.0.6.dist-info/METADATA
ipelago-0.0.6.dist-info/RECORD
