Metadata-Version: 2.1
Name: ipelago
Version: 0.0.6
Summary: ipelago: CLI personal microblog (命令行个人微博客)
Author-email: ahui <102419@gmail.com>
Requires-Python: >=3.10
Classifier: License :: OSI Approved :: MIT License
Requires-Dist: arrow
Requires-Dist: click
Requires-Dist: appdirs
Requires-Dist: pyperclip
Requires-Dist: result
Requires-Dist: requests
Requires-Dist: humanfriendly
Requires-Dist: feedparser
Requires-Dist: beautifulsoup4
Requires-Dist: lxml
Requires-Dist: Jinja2
Project-URL: Home, https://github.com/ahui2016/pypelago
